zope/ramcache/__init__.py
zope/ramcache/ram.py
zope/ramcache/interfaces/__init__.py
zope/ramcache/interfaces/ram.py
zope/ramcache/tests/__init__.py
zope/ramcache/tests/test_icache.py
zope/ramcache/tests/test_ramcache.py
zope_ramcache-4.0.dist-info/licenses/LICENSE.txt
zope_ramcache-4.0.dist-info/METADATA
zope_ramcache-4.0.dist-info/WHEEL
zope_ramcache-4.0.dist-info/top_level.txt
zope_ramcache-4.0.dist-info/RECORD
